{
  "lastUpdated": "2025-07-08T00:00:37.275Z",
  "stats": {
    "users": {
      "count": 31237,
      "change": 2.6
    },
    "revenue": {
      "amount": 211802,
      "change": 0.4
    },
    "projects": {
      "count": 362,
      "change": -2.2
    },
    "tasks": {
      "count": 1929,
      "change": 12.1
    }
  },
  "activities": [
    {
      "type": "task",
      "title": "Project milestone reached",
      "timestamp": "2025-07-08T00:00:37.275Z"
    },
    {
      "type": "payment",
      "title": "Payment received",
      "timestamp": "2025-07-07T00:00:08.752Z"
    },
    {
      "type": "user",
      "title": "Task assigned",
      "timestamp": "2025-07-06T00:00:37.745Z"
    },
    {
      "type": "project",
      "title": "Task assigned",
      "timestamp": "2025-07-05T00:00:42.622Z"
    },
    {
      "type": "payment",
      "title": "New message",
      "timestamp": "2025-07-04T00:00:45.379Z"
    }
  ],
  "weeklyActivity": [
    {
      "day": "Mon",
      "value": 13
    },
    {
      "day": "Tue",
      "value": 30
    },
    {
      "day": "Wed",
      "value": 10
    },
    {
      "day": "Thu",
      "value": 72
    },
    {
      "day": "Fri",
      "value": 21
    },
    {
      "day": "Sat",
      "value": 22
    },
    {
      "day": "Sun",
      "value": 77
    }
  ],
  "performanceMetrics": [
    {
      "date": "2023-09-29",
      "value": 47
    },
    {
      "date": "2023-09-30",
      "value": 31
    },
    {
      "date": "2023-10-01",
      "value": 23
    },
    {
      "date": "2023-10-02",
      "value": 10
    },
    {
      "date": "2023-10-03",
      "value": 28
    },
    {
      "date": "2023-10-04",
      "value": 27
    },
    {
      "date": "2023-10-05",
      "value": 31
    }
  ]
}